sg2.cp312-win_amd64.pyd
sg2-2.3.3.dist-info/COPYING
sg2-2.3.3.dist-info/METADATA
sg2-2.3.3.dist-info/WHEEL
sg2-2.3.3.dist-info/top_level.txt
sg2-2.3.3.dist-info/RECORD
